{
  "kind": "collectionType",
  "collectionName": "homes",
  "info": {
    "name": "home",
    "description": ""
  },
  "options": {
    "increments": true,
    "timestamps": true,
    "draftAndPublish": true
  },
  "pluginOptions": {},
  "attributes": {
    "text": {
      "type": "string"
    },
    "g": {
      "model": "file",
      "via": "related",
      "allowedTypes": [
        "images",
        "files",
        "videos"
      ],
      "plugin": "upload",
      "required": false,
      "pluginOptions": {}
    },
    "ggg": {
      "type": "richtext"
    },
    "test": {
      "type": "component",
      "repeatable": true,
      "component": "test.test"
    }
  }
}
